fastaai/__init__.py
fastaai/fastaai.py
fastaai/fastaai_api.py
fastaai/00.Libraries/01.SCG_HMMs/Archaea_SCG.hmm
fastaai/00.Libraries/01.SCG_HMMs/Bacteria_SCG.hmm
fastaai/00.Libraries/01.SCG_HMMs/Complete_SCG_DB.hmm
FastAAI_release-0.0.1.dist-info/LICENSE
FastAAI_release-0.0.1.dist-info/METADATA
FastAAI_release-0.0.1.dist-info/WHEEL
FastAAI_release-0.0.1.dist-info/entry_points.txt
FastAAI_release-0.0.1.dist-info/top_level.txt
FastAAI_release-0.0.1.dist-info/RECORD
