Metadata-Version: 2.2
Name: FastAAI-release
Version: 0.0.1
Summary: A rapid estimator for amino acid identity between genomes.
Author: Kenji Gerhardt
Author-email: kenji.gerhardt@gmail.com
Requires-Python: >=3
License-File: LICENSE
Requires-Dist: numpy==2.2.2
Requires-Dist: pyrodigal==3.6.3
Requires-Dist: pyhmmer==0.11.0
Dynamic: author
Dynamic: author-email
Dynamic: description
Dynamic: description-content-type
Dynamic: requires-dist
Dynamic: requires-python
Dynamic: summary
